README.md
setup.cfg
setup.py
storeql/__init__.py
storeql/__main__.py
storeql.egg-info/PKG-INFO
storeql.egg-info/SOURCES.txt
storeql.egg-info/dependency_links.txt
storeql.egg-info/entry_points.txt
storeql.egg-info/requires.txt
storeql.egg-info/top_level.txt
storeql/commands/__init__.py
storeql/commands/connection.py
storeql/commands/findpw.py
storeql/commands/greetings.py
storeql/commands/storepw.py