Metadata-Version: 1.1
Name: storeql
Version: 1.0.2
Summary: Storeql is a CLI to store your passwords!
Home-page: https://github.com/Kiraixda/storeql
Author: Kirai
Author-email: allerborndaniel54@gmail.com
License: UNKNOWN
Download-URL: https://github.com/Kiraixda/storeql/archive/refs/tags/1.0.2.tar.gz
Keywords: FAST,VAULT,CLI
Platform: UNKNOWN
